hanzilvlib/__init__.py
hanzilvlib/level.json
hanzilvlib/level.py
hanzilvlib-0.1.3.dist-info/LICENSE
hanzilvlib-0.1.3.dist-info/WHEEL
hanzilvlib-0.1.3.dist-info/METADATA
hanzilvlib-0.1.3.dist-info/RECORD
