Metadata-Version: 2.1
Name: hanzilvlib
Version: 0.1.3
Summary: A library to view contents from HanziLevelProject
Home-page: https://github.com/patarapolw/hanzilvlib
License: MIT
Keywords: hanzi,chinese
Author: Pacharapol Withayasakpunt
Author-email: patarapolw@gmail.com
Requires-Python: >=3.5
Classifier: License :: OSI Approved :: MIT License
Classifier: Programming Language :: Python :: 3
Classifier: Programming Language :: Python :: 3.5
Classifier: Programming Language :: Python :: 3.6
Classifier: Programming Language :: Python :: 3.7
Requires-Dist: importlib_resources (>=1.0,<2.0)
